tinyalign/_core.cpython-312-x86_64-linux-gnu.so
tinyalign/_version.pyi
tinyalign/__init__.py
tinyalign/_core.pyi
tinyalign/_version.py
tinyalign/py.typed
tinyalign-0.2.2.dist-info/WHEEL
tinyalign-0.2.2.dist-info/RECORD
tinyalign-0.2.2.dist-info/top_level.txt
tinyalign-0.2.2.dist-info/METADATA
tinyalign-0.2.2.dist-info/LICENSE
