Metadata-Version: 2.1
Name: tinyalign
Version: 0.2.2
Summary: Fast banded edit distance
Author-email: Marcel Martin <marcel.martin@scilifelab.se>
License: MIT
Project-URL: Homepage, https://github.com/marcelm/tinyalign/
Classifier: Development Status :: 4 - Beta
Classifier: Intended Audience :: Science/Research
Classifier: License :: OSI Approved :: MIT License
Classifier: Natural Language :: English
Classifier: Programming Language :: Cython
Classifier: Programming Language :: Python :: 3
Classifier: Topic :: Scientific/Engineering :: Bio-Informatics
Requires-Python: >=3.7
License-File: LICENSE
